documentapi/__init__.py
documentapi/api.py
documentapi/exception.py
document_lib_python-0.1.0.dist-info/LICENSE
document_lib_python-0.1.0.dist-info/METADATA
document_lib_python-0.1.0.dist-info/WHEEL
document_lib_python-0.1.0.dist-info/top_level.txt
document_lib_python-0.1.0.dist-info/RECORD
