Metadata-Version: 2.1
Name: document-lib-python
Version: 0.1.0
Summary: Document Library API for Python
Author-email: Julian Nguyen <jnguyen@aerospike.com>
Project-URL: Homepage, https://github.com/aerospike/document-lib-python
Project-URL: Bug Tracker, https://github.com/aerospike/document-lib-python/issues
Classifier: Programming Language :: Python :: 3
Requires-Python: <=3.9.13,>=3.7.0
License-File: LICENSE
Requires-Dist: jsonpath-ng-aerospike (==1.5.3)
Requires-Dist: aerospike (==7.0.2)
